pycr/__init__.py
pycr/analyze.py
pycr/assessment.py
pycr/ct1.csv
pycr/ct3.csv
pycr/helper.py
pycr/mock.py
pycr/testing.py
pycr-0.0.0.9001.dist-info/DESCRIPTION.rst
pycr-0.0.0.9001.dist-info/METADATA
pycr-0.0.0.9001.dist-info/RECORD
pycr-0.0.0.9001.dist-info/WHEEL
pycr-0.0.0.9001.dist-info/metadata.json
pycr-0.0.0.9001.dist-info/top_level.txt
