Metadata-Version: 2.0
Name: pycr
Version: 0.0.0.9001
Summary: Analyzing Real-Time Quantitative PCR Data
Home-page: https://github.com/MahShaaban/pycr
Author: Mahmoud Ahmed
Author-email: mahmoud.s.fahmy@students.kasralainy.edu.eg
License: GPL-3
Platform: UNKNOWN
Requires-Dist: markdown
Requires-Dist: numpy
Requires-Dist: pandas
Requires-Dist: scipy
